byu_awslogin/__init__.py
byu_awslogin/__version__.py
byu_awslogin/auth/__init__.py
byu_awslogin/auth/adfs_auth.py
byu_awslogin/auth/assume_role.py
byu_awslogin/auth/saml.py
byu_awslogin/index.py
byu_awslogin/login.py
byu_awslogin/util/__init__.py
byu_awslogin/util/consoleeffects.py
byu_awslogin/util/data_cache.py
byu_awslogin-0.15.2.dist-info/entry_points.txt
byu_awslogin-0.15.2.dist-info/LICENSE
byu_awslogin-0.15.2.dist-info/WHEEL
byu_awslogin-0.15.2.dist-info/METADATA
byu_awslogin-0.15.2.dist-info/RECORD
