Metadata-Version: 2.1
Name: byu-awslogin
Version: 0.15.2
Summary: An aws-adfs spinoff that fits BYU's needs
Home-page: https://github.com/byu-oit/awslogin
License: Apache-2.0
Author: BYU OIT Application Development
Author-email: it@byu.edu
Requires-Python: >=2.7, !=3.0.*, !=3.1.*, !=3.2.*, !=3.3.*, !=3.4.*
Classifier: License :: OSI Approved :: Apache Software License
Classifier: Programming Language :: Python :: 2
Classifier: Programming Language :: Python :: 2.7
Classifier: Programming Language :: Python :: 3
Classifier: Programming Language :: Python :: 3.5
Classifier: Programming Language :: Python :: 3.6
Classifier: Programming Language :: Python :: 3.7
Classifier: Programming Language :: Python :: 3.8
Classifier: Programming Language :: Python :: 3.9
Requires-Dist: beautifulsoup4 (>=4.7,<5.0)
Requires-Dist: boto3 (>=1.9,<2.0)
Requires-Dist: click (>=7.0,<8.0)
Requires-Dist: configparser (>=3.7,<5.0)
Requires-Dist: future (>=0.17.1,<0.19.0)
Requires-Dist: lxml (>=4.3,<5.0)
Requires-Dist: prompt-toolkit (>=2.0,<3.0)
Requires-Dist: requests (>=2.21,<3.0)
Project-URL: Repository, https://github.com/byu-oit/awslogin
